level-1/level-2/level-3/encoder_dec_to_bcd.v
module encoder_dec_to_bcd(input wire [9:0] DEC, input wire EN,
                          output reg [3:0] BCD, output reg AI);


    always @(DEC) begin

        if(!EN) begin
            case(DEC)
                10'b0000000001: BCD = 4'b0000;
                10'b0000000010: BCD = 4'b0001;
                10'b0000000100: BCD = 4'b0010;
                10'b0000001000: BCD = 4'b0011;
                10'b0000010000: BCD = 4'b0100;
                10'b0000100000: BCD = 4'b0101;
                10'b0001000000: BCD = 4'b0110;
                10'b0010000000: BCD = 4'b0111;
                10'b0100000000: BCD = 4'b1000;
                10'b1000000000: BCD = 4'b1001;
            default:
                BCD = 4'b0000;
            endcase

            AI = (DEC != 0);
        end
        else begin
            BCD = 0;
            AI = 0;
        end
    end
endmodule

level-1/level-2/level-3/encoder_dec_to_bcd_tb.v
`include "encoder_dec_to_bcd.v"

module encoder_dec_to_bcd_tb();
    reg [9:0] DEC;
    reg EN;
    wire [3:0] BCD;
    wire AI;

    encoder_dec_to_bcd dut(DEC, EN, BCD, AI);

    initial begin
        EN = 0; #10;
        DEC = 10'b0000000001; #10;
        DEC = 10'b0000000010; #10;
        DEC = 10'b0000000100; #10;
        DEC = 10'b0000001000; #10;
        DEC = 10'b0000010000; #10;
        DEC = 10'b0000100000; #10;
        DEC = 10'b0001000000; #10;
        DEC = 10'b0010000000; #10;
        DEC = 10'b0100000000; #10;
        DEC = 10'b1000000000; #10;

        DEC = 10'b0000000000; #10;

        EN = 1; #10;
        DEC = 10'b0000000001; #10;
        DEC = 10'b0000000010; #10;
        DEC = 10'b0000000100; #10;
        DEC = 10'b0000001000; #10;
        DEC = 10'b0000010000; #10;
        DEC = 10'b0000100000; #10;
        DEC = 10'b0001000000; #10;
        DEC = 10'b0010000000; #10;
        DEC = 10'b0100000000; #10;
        DEC = 10'b1000000000; #10;

        DEC = 10'b0000000000; #10;

        EN = 0; #10;
        DEC = 10'b0000100001; #10;
        DEC = 10'b0000000010; #10;
        DEC = 10'b1000000100; #10;
        DEC = 10'b0000001000; #10;
        DEC = 10'b0000010000; #10;
        DEC = 10'b0000101000; #10;
        DEC = 10'b0001000000; #10;
        DEC = 10'b0010000000; #10;
        DEC = 10'b0100000000; #10;
        DEC = 10'b1000000001; #10;

        DEC = 10'b0000000000; #10;
    end


    initial begin
        $dumpfile("encoder_dec_to_bcd_tb.vcd");
        $dumpvars(0, encoder_dec_to_bcd_tb);
    end

endmodule

level-1/level-2/level-3/encoder_dec_to_bcd_tb.vcd
$date
	Sun May  8 20:45:09 2022
$end
$version
	Icarus Verilog
$end
$timescale
	1s
$end
$scope module encoder_dec_to_bcd_tb $end
$var wire 4 ! BCD [3:0] $end
$var wire 1 " AI $end
$var reg 10 # DEC [9:0] $end
$var reg 1 $ EN $end
$scope module dut $end
$var wire 10 % DEC [9:0] $end
$var wire 1 $ EN $end
$var reg 1 " AI $end
$var reg 4 & BCD [3:0] $end
$upscope $end
$upscope $end
$enddefinitions $end
#0
$dumpvars
bx &
bx %
0$
bx #
x"
bx !
$end
#10
1"
b0 !
b0 &
b1 #
b1 %
#20
b1 !
b1 &
b10 #
b10 %
#30
b10 !
b10 &
b100 #
b100 %
#40
b11 !
b11 &
b1000 #
b1000 %
#50
b100 !
b100 &
b10000 #
b10000 %
#60
b101 !
b101 &
b100000 #
b100000 %
#70
b110 !
b110 &
b1000000 #
b1000000 %
#80
b111 !
b111 &
b10000000 #
b10000000 %
#90
b1000 !
b1000 &
b100000000 #
b100000000 %
#100
b1001 !
b1001 &
b1000000000 #
b1000000000 %
#110
0"
b0 !
b0 &
b0 #
b0 %
#120
1$
#130
b1 #
b1 %
#140
b10 #
b10 %
#150
b100 #
b100 %
#160
b1000 #
b1000 %
#170
b10000 #
b10000 %
#180
b100000 #
b100000 %
#190
b1000000 #
b1000000 %
#200
b10000000 #
b10000000 %
#210
b100000000 #
b100000000 %
#220
b1000000000 #
b1000000000 %
#230
b0 #
b0 %
#240
0$
#250
1"
b100001 #
b100001 %
#260
b1 !
b1 &
b10 #
b10 %
#270
b0 !
b0 &
b1000000100 #
b1000000100 %
#280
b11 !
b11 &
b1000 #
b1000 %
#290
b100 !
b100 &
b10000 #
b10000 %
#300
b0 !
b0 &
b101000 #
b101000 %
#310
b110 !
b110 &
b1000000 #
b1000000 %
#320
b111 !
b111 &
b10000000 #
b10000000 %
#330
b1000 !
b1000 &
b100000000 #
b100000000 %
#340
b0 !
b0 &
b1000000001 #
b1000000001 %
#350
0"
b0 #
b0 %
