level-1/level-2/level-3/mux_2to1_tb.v
`include "mux_2to1.v"

module mux_2to1_tb;
    reg OUT;
    wire SEL;
    wire D0;
    wire D1;

    mux_2to1_dut(SEL, D0, D1, OUT);

    initial begin

        SEL = 1'b0 #10;
        D0 = 1'b0; D1 = 1'b0; #10;
        D0 = 1'b0; D1 = 1'b1; #10;
        D0 = 1'b1; D1 = 1'b0; #10;
        D0 = 1'b1; D1 = 1'b1; #10;

        SEL = 1'b1 #10;
        D0 = 1'b0; D1 = 1'b0; #10;
        D0 = 1'b0; D1 = 1'b1; #10;
        D0 = 1'b1; D1 = 1'b0; #10;
        D0 = 1'b1; D1 = 1'b1; #10;

    end

    initial begin
        $dumpfile("mux_2to1_tb.vcd");
        $dumpvars(0, mux_2to1_tb);
    end

endmodule

level-1/level-2/level-3/mux_2to1_tb.vcd
$date
	Sun May  8 19:21:48 2022
$end
$version
	Icarus Verilog
$end
$timescale
	1s
$end
$scope module mux_2to1_tb $end
$var wire 1 ! OUT $end
$var reg 1 " D0 $end
$var reg 1 # D1 $end
$var reg 1 $ SEL $end
$scope module dut $end
$var wire 1 " D0 $end
$var wire 1 # D1 $end
$var wire 1 $ SEL $end
$var reg 1 ! OUT $end
$upscope $end
$upscope $end
$enddefinitions $end
#0
$dumpvars
0$
x#
x"
x!
$end
#10
0!
0#
0"
#20
1#
#30
1!
0#
1"
#40
1#
#50
0!
0#
0"
#60
1$
#80
1!
1#
#90
0!
0#
1"
#100
1!
1#
#110
0!
0#
0"
